LICENSE
README.md
setup.py
src/datafev/__init__.py
src/datafev.egg-info/PKG-INFO
src/datafev.egg-info/SOURCES.txt
src/datafev.egg-info/dependency_links.txt
src/datafev.egg-info/not-zip-safe
src/datafev.egg-info/requires.txt
src/datafev.egg-info/top_level.txt
src/datafev/algorithms/__init__.py
src/datafev/algorithms/cluster/__init__.py
src/datafev/algorithms/cluster/pricing_rule.py
src/datafev/algorithms/cluster/prioritization_llf.py
src/datafev/algorithms/cluster/rescheduling_milp.py
src/datafev/algorithms/multi_cluster/__init__.py
src/datafev/algorithms/multi_cluster/rescheduling_milp.py
src/datafev/algorithms/vehicle/__init__.py
src/datafev/algorithms/vehicle/routing_milp.py
src/datafev/algorithms/vehicle/scheduling_lp.py
src/datafev/algorithms/vehicle/scheduling_milp.py
src/datafev/data_handling/__init__.py
src/datafev/data_handling/charger.py
src/datafev/data_handling/cluster.py
src/datafev/data_handling/fleet.py
src/datafev/data_handling/multi_cluster.py
src/datafev/data_handling/vehicle.py
src/datafev/routines/__init__.py
src/datafev/routines/arrival.py
src/datafev/routines/departure.py
src/datafev/routines/charging_control/__init__.py
src/datafev/routines/charging_control/centralized_milp.py
src/datafev/routines/charging_control/decentralized_fcfs.py
src/datafev/routines/charging_control/decentralized_llf.py
src/datafev/routines/charging_control/decentralized_milp.py
src/datafev/routines/scenario_generation/__init__.py
src/datafev/routines/scenario_generation/sceneration.py
src/datafev/routines/scenario_generation/utils.py
src/datafev/routines/simple_reservation/__init__.py
src/datafev/routines/simple_reservation/arrival.py
src/datafev/routines/simple_reservation/reservation.py
src/datafev/routines/smart_reservation/__init__.py
src/datafev/routines/smart_reservation/arrival.py
src/datafev/routines/smart_reservation/reservation.py
src/tutorials/__init__.py
src/tutorials/scenario_generation/__init__.py
src/tutorials/scenario_generation/scenario_generation_conditional_pdfs.py
src/tutorials/scenario_generation/scenario_generation_simple_pdfs.py
src/tutorials/simulations/__init__.py
src/tutorials/simulations/example_01_no_reservations.py
