Metadata-Version: 2.1
Name: datafev
Version: 1.0.0
Summary: A Python framework for development and testing of management algorithms for electric vehicle charging infrastructures
Home-page: https://github.com/erdemgumrukcu/datafev
Author: Institute for Automation of Complex Power Systems (ACS),E.ON Energy Research Center (E.ON ERC),RWTH Aachen University
Author-email: post_acs@eonerc.rwth-aachen.de
License: MIT
Platform: any
Classifier: Development Status :: 5 - Production/Stable
Classifier: Operating System :: OS Independent
Classifier: Intended Audience :: Science/Research
Classifier: License :: OSI Approved :: MIT License
Classifier: Topic :: Scientific/Engineering
Classifier: Natural Language :: English
Classifier: Programming Language :: Python :: 3.6
Requires-Python: >=3.6
License-File: LICENSE
